xudoku/__init__.py
xudoku/sudoku.py
xudoku-1.0.0.dist-info/entry_points.txt
xudoku-1.0.0.dist-info/LICENSE
xudoku-1.0.0.dist-info/WHEEL
xudoku-1.0.0.dist-info/METADATA
xudoku-1.0.0.dist-info/RECORD
