Metadata-Version: 2.1
Name: xudoku
Version: 1.0.0
Summary: Solve sudoku using an 'exact cover' algorithm.
Home-page: https://github.com/jwg4/xudoku
License: GPL-2.0-only
Author: Moy Easwaran
Maintainer: Jack Grahl
Maintainer-email: jack.grahl@gmail.com
Requires-Python: >=3.7.1,<4.0.0
Classifier: License :: OSI Approved :: GNU General Public License v2 (GPLv2)
Classifier: Programming Language :: Python :: 3
Classifier: Programming Language :: Python :: 3.8
Classifier: Programming Language :: Python :: 3.9
Requires-Dist: exact-cover (>=0.4.3,<0.5.0)
Project-URL: Repository, https://github.com/jwg4/xudoku
